impunity/__init__.py
impunity/exception.py
impunity/py.typed
impunity/quantityNode.py
impunity/visitor.py
impunity/wrapper.py
impunity-1.0.5.dist-info/METADATA
impunity-1.0.5.dist-info/WHEEL
impunity-1.0.5.dist-info/RECORD
