Metadata-Version: 2.3
Name: impunity
Version: 1.0.5
Summary: Static checking for consistency of physical units
Author-email: Antoine Chevrot <antoine.chevrot@gmail.com>, Xavier Olive <git@xoolive.org>
License: MIT
Requires-Python: >=3.9
Requires-Dist: astor>=0.8.1
Requires-Dist: pint>=0.24.4
Requires-Dist: typing-extensions>=4.12.2
